utensil/__init__.py
utensil/constant/__init__.py
utensil/constant/_constant.py
utensil/constant/connector_info.py
utensil/general/__init__.py
utensil/general/_general.py
utensil/general/logger.py
utensil/loopflow/__init__.py
utensil/loopflow/functions/__init__.py
utensil/loopflow/functions/basic.py
utensil/loopflow/functions/dataflow.py
utensil/loopflow/loopflow.py
utensil/random_search/__init__.py
utensil/random_search/_random_search.py
utensil-0.0.2.dist-info/WHEEL
utensil-0.0.2.dist-info/METADATA
utensil-0.0.2.dist-info/RECORD
