Metadata-Version: 2.1
Name: utensil
Version: 0.0.2
Summary: A useful utensil kit for machine learning.
Home-page: https://github.com/HYChou0515/utensil
License: BSD-3-Clause
Keywords: flow,machine learning
Author: Chou Hung-Yi
Author-email: hychou.svm@gmail.com
Maintainer: Chou Hung-Yi
Maintainer-email: hychou.svm@gmail.com
Requires-Python: >=3.7.4,<4
Classifier: Development Status :: 1 - Planning
Classifier: License :: OSI Approved :: BSD License
Classifier: Programming Language :: Python :: 3
Classifier: Programming Language :: Python :: 3.10
Classifier: Programming Language :: Python :: 3.8
Classifier: Programming Language :: Python :: 3.9
Classifier: Topic :: Scientific/Engineering
Classifier: Topic :: Software Development :: Libraries :: Python Modules
Classifier: Topic :: Utilities
Provides-Extra: loguru
Provides-Extra: loopflow
Requires-Dist: PyYAML (>=5.4.1,<6.0.0); extra == "loopflow"
Requires-Dist: loguru (>=0.5.3,<0.6.0); extra == "loguru"
Requires-Dist: pandas (>=1.3.3,<2.0.0); extra == "loopflow"
Requires-Dist: scikit-learn (>=1.0,<2.0); extra == "loopflow"
Requires-Dist: xgboost (>=1.4.2,<2.0.0); extra == "loopflow"
Project-URL: Documentation, https://www.hychou.dev
Project-URL: Repository, https://github.com/HYChou0515/utensil
